detectinhos/__init__.py
detectinhos/anchors.py
detectinhos/batch.py
detectinhos/dataset.py
detectinhos/encode.py
detectinhos/inference.py
detectinhos/loss.py
detectinhos/matching.py
detectinhos/metrics.py
detectinhos/sample.py
detectinhos/sublosses.py
detectinhos/tasks/__init__.py
detectinhos/tasks/standard.py
detectinhos-0.0.1.dist-info/METADATA
detectinhos-0.0.1.dist-info/WHEEL
detectinhos-0.0.1.dist-info/entry_points.txt
detectinhos-0.0.1.dist-info/top_level.txt
detectinhos-0.0.1.dist-info/RECORD
