Metadata-Version: 2.4
Name: detectinhos
Version: 0.0.1
Summary: Read frames from OpenCV like humans
Requires-Dist: opencv-python
Requires-Dist: numpy<2
Requires-Dist: torch
Requires-Dist: torchvision
Requires-Dist: dacite
Requires-Dist: dataclasses-json
Requires-Dist: torchvision
Requires-Dist: mean-average-precision
Requires-Dist: toolz
